reader_writer_lock/Base.py
reader_writer_lock/MpFactory.py
reader_writer_lock/MtFactory.py
reader_writer_lock/ReadLock.py
reader_writer_lock/WriteLock.py
reader_writer_lock/__init__.py
reader_writer_locks-0.0.3.dist-info/LICENSE.txt
reader_writer_locks-0.0.3.dist-info/METADATA
reader_writer_locks-0.0.3.dist-info/WHEEL
reader_writer_locks-0.0.3.dist-info/top_level.txt
reader_writer_locks-0.0.3.dist-info/RECORD
