Metadata-Version: 2.1
Name: reader-writer-locks
Version: 0.0.3
Summary: Reader Writer Lock
Home-page: UNKNOWN
Author: Viet Le
Author-email: minhviet810business@gmail.com
License: MIT
Project-URL: Source, https://github.com/leminhviett/ReaderWriterLock
Keywords: concurrency,multithreading,multiprocessing
Platform: UNKNOWN
Classifier: Development Status :: 4 - Beta
Classifier: Intended Audience :: Developers
Classifier: Programming Language :: Python :: 3
Classifier: Operating System :: OS Independent
